pyteda/__init__.py
pyteda/analysis/__init__.py
pyteda/analysis/analysis_core.py
pyteda/analysis/analysis_enkf.py
pyteda/analysis/analysis_enkf_bloc.py
pyteda/analysis/analysis_enkf_cholesky.py
pyteda/analysis/analysis_enkf_modified_cholesky.py
pyteda/analysis/analysis_enkf_naive.py
pyteda/analysis/analysis_enkf_shrinkage_precision.py
pyteda/analysis/analysis_ensrf.py
pyteda/analysis/analysis_etkf.py
pyteda/analysis/analysis_factory.py
pyteda/analysis/analysis_lenkf.py
pyteda/analysis/analysis_letkf.py
pyteda/analysis/loader.py
pyteda/analysis/registry.py
pyteda/background/__init__.py
pyteda/background/background_core.py
pyteda/models/__init__.py
pyteda/models/lorenz96.py
pyteda/models/model.py
pyteda/models/quasi_geostrophic.py
pyteda/observation/__init__.py
pyteda/observation/observation_core.py
pyteda/simulation/__init__.py
pyteda/simulation/simulation_core.py
pyteda-0.2.5.dist-info/METADATA
pyteda-0.2.5.dist-info/WHEEL
pyteda-0.2.5.dist-info/top_level.txt
pyteda-0.2.5.dist-info/RECORD
