Metadata-Version: 2.4
Name: pyteda
Version: 0.2.5
Summary: TEDA: Toy models and ensemble-based Data Assimilation methods for education and experimentation
Author-email: "Elías D. Niño-Ruiz" <elias.d.nino@gmail.com>
License: MIT
Keywords: data assimilation,EnKF,education,Lorenz96,Python
Classifier: Development Status :: 3 - Alpha
Classifier: Intended Audience :: Education
Classifier: Topic :: Scientific/Engineering :: Atmospheric Science
Classifier: License :: OSI Approved :: MIT License
Classifier: Programming Language :: Python :: 3
Classifier: Programming Language :: Python :: 3.7
Classifier: Programming Language :: Python :: 3.8
Classifier: Programming Language :: Python :: 3.9
Requires-Python: >=3.7
Requires-Dist: numpy
Requires-Dist: scipy
Requires-Dist: matplotlib
Requires-Dist: scikit-learn
